star_alchemy/__init__.py
star_alchemy/_star_schema.py
star_alchemy-0.6.0.dist-info/LICENSE
star_alchemy-0.6.0.dist-info/METADATA
star_alchemy-0.6.0.dist-info/WHEEL
star_alchemy-0.6.0.dist-info/RECORD
